cvxpygen/__init__.py
cvxpygen/cpg.py
cvxpygen/mappings.py
cvxpygen/mpqp.py
cvxpygen/solvers.py
cvxpygen/utils.py
cvxpygen/solvers/Clarabel.cpp/.clang-format
cvxpygen/solvers/Clarabel.cpp/.git
cvxpygen/solvers/Clarabel.cpp/.gitignore
cvxpygen/solvers/Clarabel.cpp/.gitmodules
cvxpygen/solvers/Clarabel.cpp/CMakeLists.txt
cvxpygen/solvers/Clarabel.cpp/LICENSE.md
cvxpygen/solvers/Clarabel.cpp/README.md
cvxpygen/solvers/Clarabel.cpp/Clarabel.rs/Cargo.toml
cvxpygen/solvers/Clarabel.cpp/Clarabel.rs/pyproject.toml
cvxpygen/solvers/Clarabel.cpp/Clarabel.rs/rustfmt.toml
cvxpygen/solvers/Clarabel.cpp/Clarabel.rs/src/lib.rs
cvxpygen/solvers/Clarabel.cpp/Clarabel.rs/src/algebra/adjoint.rs
cvxpygen/solvers/Clarabel.cpp/Clarabel.rs/src/algebra/error_types.rs
cvxpygen/solvers/Clarabel.cpp/Clarabel.rs/src/algebra/floats.rs
cvxpygen/solvers/Clarabel.cpp/Clarabel.rs/src/algebra/math_traits.rs
cvxpygen/solvers/Clarabel.cpp/Clarabel.rs/src/algebra/matrix_traits.rs
cvxpygen/solvers/Clarabel.cpp/Clarabel.rs/src/algebra/matrix_types.rs
cvxpygen/solvers/Clarabel.cpp/Clarabel.rs/src/algebra/mod.rs
cvxpygen/solvers/Clarabel.cpp/Clarabel.rs/src/algebra/reshaped.rs
cvxpygen/solvers/Clarabel.cpp/Clarabel.rs/src/algebra/scalarmath.rs
cvxpygen/solvers/Clarabel.cpp/Clarabel.rs/src/algebra/symmetric.rs
cvxpygen/solvers/Clarabel.cpp/Clarabel.rs/src/algebra/vecmath.rs
cvxpygen/solvers/Clarabel.cpp/Clarabel.rs/src/algebra/csc/block_concatenate.rs
cvxpygen/solvers/Clarabel.cpp/Clarabel.rs/src/algebra/csc/core.rs
cvxpygen/solvers/Clarabel.cpp/Clarabel.rs/src/algebra/csc/matrix_math.rs
cvxpygen/solvers/Clarabel.cpp/Clarabel.rs/src/algebra/csc/mod.rs
cvxpygen/solvers/Clarabel.cpp/Clarabel.rs/src/algebra/csc/utils.rs
cvxpygen/solvers/Clarabel.cpp/Clarabel.rs/src/algebra/dense/blas.rs
cvxpygen/solvers/Clarabel.cpp/Clarabel.rs/src/algebra/dense/blaslike_traits.rs
cvxpygen/solvers/Clarabel.cpp/Clarabel.rs/src/algebra/dense/block_concatenate.rs
cvxpygen-0.6.7.dist-info/licenses/LICENSE
cvxpygen-0.6.7.dist-info/METADATA
cvxpygen-0.6.7.dist-info/WHEEL
cvxpygen-0.6.7.dist-info/top_level.txt
cvxpygen-0.6.7.dist-info/RECORD
