Metadata-Version: 2.4
Name: cvxpygen
Version: 0.6.7
Summary: Code generation with CVXPY
Author-email: Maximilian Schaller <mschall@stanford.edu>, Goran Banjac <goranbanjac1989@gmail.com>, Bartolomeo Stellato <bstellato@princeton.edu>, Steven Diamond <diamond@cs.stanford.edu>, Akshay Agrawal <akshayka@cs.stanford.edu>, Stephen Boyd <boyd@stanford.edu>
License: Apache License, Version 2.0
Project-URL: Homepage, https://github.com/cvxgrp/cvxpygen
Requires-Python: >=3.10
License-File: LICENSE
Requires-Dist: cmake>=3.5
Requires-Dist: cvxpy>=1.6.4
Requires-Dist: pybind11>=2.8
Requires-Dist: osqp>=1.0.0b3
Requires-Dist: ecos>=2.0.14
Requires-Dist: clarabel>=0.6.0
Requires-Dist: scipy>=1.13.1
Requires-Dist: numpy>=1.26.0
Requires-Dist: qocogen>=0.1.9
Requires-Dist: qoco>=0.1.4
Requires-Dist: pdaqp>=0.6.7
Provides-Extra: dev
Requires-Dist: pytest==6.2.4; extra == "dev"
Dynamic: license-file
